{
    "DNDConfig": null,
    "__parentReadjusting__": false,
    "_height_": {
        "type": "string",
        "value": "100%"
    },
    "_margin_": [
        0,
        0,
        0,
        0
    ],
    "_orientation_": 6,
    "_padding_": [
        0,
        0,
        0,
        0
    ],
    "_percent_": true,
    "_right_": {
        "type": "string",
        "value": "0%"
    },
    "_skin_": "sf5ad049246543c5b2b260100d5eb83c",
    "_top_": {
        "type": "string",
        "value": "0%"
    },
    "_width_": {
        "type": "string",
        "value": "20%"
    },
    "allboxes": [],
    "autogrowmode": 0,
    "canUpdateUI": true,
    "children": [],
    "clipbounds": true,
    "containerweight": 100,
    "enablescrolling": true,
    "id": "flxMenuOverlay",
    "ide_onClick": "AS_FlexContainer_fd4bf78a3aca45e381be66082400e394",
    "info": null,
    "isvisible": false,
    "kuid": "id5dad55ccb6450099496fe54ccf1403",
    "layouttype": 2,
    "name": "kony.ui.FlexContainer",
    "parent": "frmHome",
    "pf": "frmHome",
    "snapgridsize": 10,
    "snaptogrid": true,
    "wType": "FlexContainer",
    "widgetalignment": 1,
    "zindex": 3
}